lm_checkpoints/__init__.py
lm_checkpoints/checkpoints.py
lm_checkpoints/evaluator.py
lm_checkpoints/multiberts.py
lm_checkpoints/pythia.py
"lm_checkpoints/test/EleutherAI/pythia-14m/step_0/results_crows_pairs_english,triviaqa.json"
lm_checkpoints/test/EleutherAI/pythia-14m/step_0/samples_crows_pairs_english.jsonl
lm_checkpoints/test/EleutherAI/pythia-14m/step_0/samples_triviaqa.jsonl
"lm_checkpoints/test/EleutherAI/pythia-14m/step_1/results_crows_pairs_english,triviaqa.json"
lm_checkpoints/test/EleutherAI/pythia-14m/step_1/samples_crows_pairs_english.jsonl
lm_checkpoints/test/EleutherAI/pythia-14m/step_1/samples_triviaqa.jsonl
"lm_checkpoints/test/EleutherAI/pythia-14m/step_2/results_crows_pairs_english,triviaqa.json"
lm_checkpoints/test/EleutherAI/pythia-14m/step_2/samples_crows_pairs_english.jsonl
lm_checkpoints/test/EleutherAI/pythia-14m/step_2/samples_triviaqa.jsonl
"lm_checkpoints/test/EleutherAI/pythia-14m/step_4/results_crows_pairs_english,triviaqa.json"
lm_checkpoints/test/EleutherAI/pythia-14m/step_4/samples_crows_pairs_english.jsonl
lm_checkpoints/test/EleutherAI/pythia-14m/step_4/samples_triviaqa.jsonl
lm_checkpoints/test_evaluator.py
lm_checkpoints/testing/__init__.py
lm_checkpoints/testing/decorators.py
lm_checkpoints-0.1.15.dist-info/entry_points.txt
lm_checkpoints-0.1.15.dist-info/LICENSE
lm_checkpoints-0.1.15.dist-info/WHEEL
lm_checkpoints-0.1.15.dist-info/METADATA
lm_checkpoints-0.1.15.dist-info/RECORD
