Metadata-Version: 2.1
Name: lm-checkpoints
Version: 0.1.15
Summary: Simple library for loading checkpoints of language models.
License: MIT
Author: Oskar van der Wal
Author-email: odw@duck.com
Requires-Python: >=3.8,<4.0
Classifier: License :: OSI Approved :: MIT License
Classifier: Programming Language :: Python :: 3
Classifier: Programming Language :: Python :: 3.8
Classifier: Programming Language :: Python :: 3.9
Classifier: Programming Language :: Python :: 3.10
Classifier: Programming Language :: Python :: 3.11
Provides-Extra: eval
Requires-Dist: accelerate (>=0.24.1,<0.25.0)
Requires-Dist: lm-eval (>=0.4.2,<0.5.0); extra == "eval"
Requires-Dist: torch (>=2.0.0,!=2.0.1,!=2.1.0)
Requires-Dist: transformers (>=4.35.0,<5.0.0)
